pylambdatest/APIGatewayLambdaTest.py
pylambdatest/AlexaLambdaTest.py
pylambdatest/BaseContext.py
pylambdatest/BaseLambdaTest.py
pylambdatest/CloudFormationLambdaTest.py
pylambdatest/CodeCommitLambdaTest.py
pylambdatest/CodePipelineLambdaTest.py
pylambdatest/__init__.py
PyLambdaTest-0.2.1.dist-info/LICENSE
PyLambdaTest-0.2.1.dist-info/METADATA
PyLambdaTest-0.2.1.dist-info/WHEEL
PyLambdaTest-0.2.1.dist-info/top_level.txt
PyLambdaTest-0.2.1.dist-info/RECORD
