Metadata-Version: 2.1
Name: PyLambdaTest
Version: 0.2.1
Summary: A simple Python library for testing AWS Lambda functions.
Home-page: https://github.com/deino475/PyLambdaTest
Author: Nile Dixon
Author-email: niledixon475@gmail.com
License: GNU GPL-V2
Platform: UNKNOWN
Requires-Python: >=3.6
License-File: LICENSE
